Metadata-Version: 1.0
Name: ajd-distributions
Version: 1.0
Summary: Gaussian and Binomial distributions
Home-page: UNKNOWN
Author: Arkojyoti Das
Author-email: arkojyotidas18@gmail.com
License: UNKNOWN
Platform: UNKNOWN
